typetree_unity/__init__.py
typetree_unity/__main__.py
typetree_unity/assembly_loader.py
typetree_unity/exporter.py
typetree_unity/generator.py
typetree_unity/libs/AssetStudio/AssetStudio.PInvoke.dll
typetree_unity/libs/AssetStudio/AssetStudio.dll
typetree_unity/libs/AssetStudio/AssetStudioFBXWrapper.dll
typetree_unity/libs/AssetStudio/AssetStudioUtility.dll
typetree_unity/libs/AssetStudio/K4os.Compression.LZ4.dll
typetree_unity/libs/AssetStudio/Mono.Cecil.Mdb.dll
typetree_unity/libs/AssetStudio/Mono.Cecil.Pdb.dll
typetree_unity/libs/AssetStudio/Mono.Cecil.Rocks.dll
typetree_unity/libs/AssetStudio/Mono.Cecil.dll
typetree_unity/libs/AssetStudio/SixLabors.Fonts.dll
typetree_unity/libs/AssetStudio/SixLabors.ImageSharp.Drawing.dll
typetree_unity/libs/AssetStudio/SixLabors.ImageSharp.dll
typetree_unity/libs/AssetStudio/Texture2DDecoderWrapper.dll
typetree_unity/libs/AssetStudio/runtimeconfig.json
typetree_unity-0.4.0a0.dist-info/LICENSE
typetree_unity-0.4.0a0.dist-info/METADATA
typetree_unity-0.4.0a0.dist-info/WHEEL
typetree_unity-0.4.0a0.dist-info/top_level.txt
typetree_unity-0.4.0a0.dist-info/RECORD
