Metadata-Version: 2.1
Name: typetree-unity
Version: 0.4.0a0
Summary: Type tree generator from Unity assemblies
Home-page: https://github.com/jrobinson3k1/typetree_unity
License: MIT License
Keywords: python,data-mining,unity,python-3,pythonnet
Platform: UNKNOWN
Classifier: Development Status :: 3 - Alpha
Classifier: License :: OSI Approved :: MIT License
Classifier: Programming Language :: Python
Classifier: Programming Language :: Python :: 3
Classifier: Programming Language :: Python :: 3.8
Classifier: Programming Language :: Python :: 3.9
Classifier: Programming Language :: Python :: 3.10
License-File: LICENSE
Requires-Dist: pythonnet (>=3.0.0a1)
